sanice/__init__.py
sanice/core.py
sanice-1.1.0.dist-info/licenses/LICENSE
tests/__init__.py
tests/test_core.py
sanice-1.1.0.dist-info/METADATA
sanice-1.1.0.dist-info/WHEEL
sanice-1.1.0.dist-info/entry_points.txt
sanice-1.1.0.dist-info/top_level.txt
sanice-1.1.0.dist-info/RECORD
