Metadata-Version: 2.4
Name: sanice
Version: 1.1.0
Summary: Biblioteca fluente para Data Science ágil (ETL, AutoML e Plotting).
Home-page: https://github.com/wSanice/sanice
Author: wSanice
Author-email: wansanice@proton.me
Project-URL: Homepage, https://github.com/wSanice/sanice
Project-URL: Source, https://github.com/wSanice/sanice
Project-URL: Funding, https://github.com/sponsors/wSanice
Classifier: Programming Language :: Python :: 3
Classifier: License :: OSI Approved :: Apache Software License
Classifier: Operating System :: OS Independent
Classifier: Intended Audience :: Developers
Classifier: Intended Audience :: Science/Research
Classifier: Topic :: Scientific/Engineering :: Artificial Intelligence
Requires-Python: >=3.8
License-File: LICENSE
Requires-Dist: numpy>=1.21.0
Requires-Dist: pandas>=2.0.0
Requires-Dist: matplotlib>=3.7.0
Requires-Dist: seaborn>=0.12.0
Requires-Dist: scikit-learn>=1.2.0
Requires-Dist: joblib>=1.2.0
Requires-Dist: openpyxl>=3.1.0
Requires-Dist: pyarrow>=11.0.0
Requires-Dist: sqlalchemy>=2.0.0
Requires-Dist: unidecode>=1.3.0
Provides-Extra: api
Requires-Dist: fastapi>=0.95.0; extra == "api"
Requires-Dist: uvicorn>=0.22.0; extra == "api"
Requires-Dist: pydantic>=1.10.0; extra == "api"
Provides-Extra: db
Requires-Dist: pymongo; extra == "db"
Requires-Dist: psycopg2-binary; extra == "db"
Requires-Dist: pymysql; extra == "db"
Provides-Extra: dev
Requires-Dist: pytest; extra == "dev"
Requires-Dist: twine; extra == "dev"
Requires-Dist: wheel; extra == "dev"
Requires-Dist: pytest-mock; extra == "dev"
Requires-Dist: coverage; extra == "dev"
Dynamic: author
Dynamic: author-email
Dynamic: classifier
Dynamic: description
Dynamic: description-content-type
Dynamic: home-page
Dynamic: license-file
Dynamic: project-url
Dynamic: provides-extra
Dynamic: requires-dist
Dynamic: requires-python
Dynamic: summary
